acace_text_preprocessor/__init__.py
acace_text_preprocessor-0.1.1.dist-info/LICENSE
acace_text_preprocessor-0.1.1.dist-info/METADATA
acace_text_preprocessor-0.1.1.dist-info/WHEEL
acace_text_preprocessor-0.1.1.dist-info/RECORD
