Metadata-Version: 2.3
Name: acace_text_preprocessor
Version: 0.1.1
Summary: Text preprocessing utilities for ACACE
Author: ACACE Team
Author-email: team@acace.ai
Requires-Python: >=3.8,<4.0
Classifier: Programming Language :: Python :: 3
Classifier: Programming Language :: Python :: 3.8
Classifier: Programming Language :: Python :: 3.9
Classifier: Programming Language :: Python :: 3.10
Classifier: Programming Language :: Python :: 3.11
Classifier: Programming Language :: Python :: 3.12
Classifier: Programming Language :: Python :: 3.13
Requires-Dist: nltk (>=3.8.1,<4.0.0)
Requires-Dist: numpy (>=1.26.3,<2.0.0)
Requires-Dist: regex (>=2023.12.25,<2024.0.0)
Requires-Dist: spacy (>=3.7.2,<4.0.0)
Requires-Dist: unidecode (>=1.3.7,<2.0.0)
